shiprocket/__init__.py
shiprocket-1.0.1.dist-info/LICENSE
shiprocket-1.0.1.dist-info/METADATA
shiprocket-1.0.1.dist-info/WHEEL
shiprocket-1.0.1.dist-info/top_level.txt
shiprocket-1.0.1.dist-info/RECORD
